MANIFEST.in
README.md
setup.py
kinesis/__init__.py
kinesis/__version__.py
kinesis/cli.py
kinesis/consumer.py
kinesis/producer.py
kinesis/settings.py
kinesis/streams.py
kinesis.egg-info/PKG-INFO
kinesis.egg-info/SOURCES.txt
kinesis.egg-info/dependency_links.txt
kinesis.egg-info/entry_points.txt
kinesis.egg-info/requires.txt
kinesis.egg-info/top_level.txt