Metadata-Version: 2.1
Name: kinesis
Version: 0.0.1a13
Summary: a kinesis consumer / producer
Home-page: https://github.com/davegallant/kinesis
Author: Dave Gallant
License: Apache License, Version 2.0
Keywords: aws,kinesis,pygments
Platform: UNKNOWN
